pyot/__init__.py
pyot/conf/__init__.py
pyot/conf/model.py
pyot/conf/pipeline.py
pyot/conf/utils.py
pyot/core/__init__.py
pyot/core/exceptions.py
pyot/core/functional.py
pyot/core/objects.py
pyot/core/queue.py
pyot/core/resources.py
pyot/core/warnings.py
pyot/docs/__init__.py
pyot/docs/__main__.py
pyot/docs/engines.py
pyot/docs/serializers.py
pyot/docs/utils.py
pyot/docs/views.py
pyot/endpoints/__init__.py
pyot/endpoints/base.py
pyot/endpoints/cdragon.py
pyot/endpoints/ddragon.py
pyot/endpoints/merakicdn.py
pyot/endpoints/riotapi.py
pyot/integrations/__init__.py
pyot/integrations/django.py
pyot/limiters/__init__.py
pyot/limiters/base.py
pyot/limiters/memory.py
pyot/limiters/redis.py
pyot/models/__init__.py
pyot/models/lol/__init__.py
pyot/models/lol/base.py
pyot/models/lol/champion.py
pyot/models/lol/championmastery.py
pyot/models/lol/championrotation.py
pyot/models/lol/clash.py
pyot/models/lol/item.py
pyot/models/lol/league.py
pyot/models/lol/match.py
pyot/models/lol/merakichampion.py
pyot/models/lol/merakiitem.py
pyot/models/lol/profileicon.py
pyot/models/lol/rune.py
pyot/models/lol/spectator.py
pyot/models/lol/spell.py
pyot/models/lol/status.py
pyot/models/lol/summoner.py
pyot/models/lol/thirdpartycode.py
pyot/models/lol/tournament.py
pyot/models/lor/__init__.py
pyot/models/lor/base.py
pyot/models/lor/card.py
pyot/models/lor/match.py
pyot/models/lor/ranked.py
pyot/models/lor/status.py
pyot/models/riot/__init__.py
pyot/models/riot/account.py
pyot/models/riot/base.py
pyot/models/tft/__init__.py
pyot/models/tft/base.py
pyot/models/tft/champion.py
pyot/models/tft/item.py
pyot/models/tft/league.py
pyot/models/tft/match.py
pyot/models/tft/profileicon.py
pyot/models/tft/summoner.py
pyot/models/tft/thirdpartycode.py
pyot/models/tft/trait.py
pyot/models/val/__init__.py
pyot/models/val/base.py
pyot/models/val/content.py
pyot/models/val/match.py
pyot/models/val/ranked.py
pyot/models/val/status.py
pyot/pipeline/__init__.py
pyot/pipeline/core.py
pyot/pipeline/expiration.py
pyot-6.0.9.dist-info/LICENSE
pyot-6.0.9.dist-info/METADATA
pyot-6.0.9.dist-info/WHEEL
pyot-6.0.9.dist-info/top_level.txt
pyot-6.0.9.dist-info/zip-safe
pyot-6.0.9.dist-info/RECORD
