Metadata-Version: 2.1
Name: pyot
Version: 6.0.9
Summary: AsyncIO-based high level Python framework Riot Games API framework that encourages rapid development and clean, pragmatic design.
Home-page: https://github.com/iann838/Pyot
Author: Jian Huang
Author-email: iann838dev@gmail.com
License: MIT
Keywords: Riot Games,League of Legends,Teamfight Tactics,Valorant,Legends of Runeterra,API,REST,asyncio
Classifier: Development Status :: 5 - Production/Stable
Classifier: Programming Language :: Python :: 3.7
Classifier: Environment :: Web Environment
Classifier: Operating System :: OS Independent
Classifier: Intended Audience :: Developers
Classifier: License :: OSI Approved :: MIT License
Classifier: Topic :: Games/Entertainment
Classifier: Topic :: Software Development :: Libraries :: Python Modules
Classifier: Natural Language :: English
License-File: LICENSE
Requires-Dist: wheel
Requires-Dist: python-dateutil >=2.8
Requires-Dist: aiohttp >=3.8
Requires-Dist: pytz
Requires-Dist: lor-deckcodes
Provides-Extra: diskcache
Requires-Dist: diskcache >=5.1 ; extra == 'diskcache'
Requires-Dist: asgiref >=3.2 ; extra == 'diskcache'
Provides-Extra: mongodb
Requires-Dist: motor >=2.3 ; extra == 'mongodb'
Provides-Extra: redis
Requires-Dist: redis[hiredis] >=4.5.0 ; extra == 'redis'
Provides-Extra: test
Requires-Dist: typeguard >=2.13 ; extra == 'test'
Requires-Dist: redis[hiredis] >=4.5.0 ; extra == 'test'
Requires-Dist: motor >=2.3 ; extra == 'test'
Requires-Dist: diskcache >=5.1 ; extra == 'test'
Requires-Dist: asgiref >=3.2 ; extra == 'test'
